mmdet/__init__.py
mmdet/version.py
mmdet/apis/__init__.py
mmdet/apis/export.py
mmdet/apis/fake_input.py
mmdet/apis/inference.py
mmdet/apis/test.py
mmdet/apis/train.py
mmdet/core/__init__.py
mmdet/core/anchor/__init__.py
mmdet/core/anchor/anchor_generator.py
mmdet/core/anchor/builder.py
mmdet/core/anchor/point_generator.py
mmdet/core/anchor/utils.py
mmdet/core/bbox/__init__.py
mmdet/core/bbox/builder.py
mmdet/core/bbox/demodata.py
mmdet/core/bbox/transforms.py
mmdet/core/bbox/assigners/__init__.py
mmdet/core/bbox/assigners/approx_max_iou_assigner.py
mmdet/core/bbox/assigners/assign_result.py
mmdet/core/bbox/assigners/atss_assigner.py
mmdet/core/bbox/assigners/base_assigner.py
mmdet/core/bbox/assigners/center_region_assigner.py
mmdet/core/bbox/assigners/grid_assigner.py
mmdet/core/bbox/assigners/hungarian_assigner.py
mmdet/core/bbox/assigners/max_iou_assigner.py
mmdet/core/bbox/assigners/point_assigner.py
mmdet/core/bbox/assigners/region_assigner.py
mmdet/core/bbox/assigners/sim_ota_assigner.py
mmdet/core/bbox/coder/__init__.py
mmdet/core/bbox/coder/base_bbox_coder.py
mmdet/core/bbox/coder/bucketing_bbox_coder.py
mmdet/core/bbox/coder/delta_xywh_bbox_coder.py
mmdet/core/bbox/coder/legacy_delta_xywh_bbox_coder.py
mmdet/core/bbox/coder/pseudo_bbox_coder.py
mmdet/core/bbox/coder/tblr_bbox_coder.py
mmdet/core/bbox/coder/yolo_bbox_coder.py
mmdet/core/bbox/iou_calculators/__init__.py
mmdet/core/bbox/iou_calculators/builder.py
mmdet/core/bbox/iou_calculators/iou2d_calculator.py
mmdet/core/bbox/match_costs/__init__.py
mmdet/core/bbox/match_costs/builder.py
mmdet/core/bbox/match_costs/match_cost.py
mmdet/core/bbox/samplers/__init__.py
mmdet/core/bbox/samplers/base_sampler.py
mmdet/core/bbox/samplers/combined_sampler.py
mmdet/core/bbox/samplers/instance_balanced_pos_sampler.py
mmdet/core/bbox/samplers/iou_balanced_neg_sampler.py
mmdet/core/bbox/samplers/ohem_sampler.py
mmdet/core/bbox/samplers/pseudo_sampler.py
mmdet/core/bbox/samplers/random_sampler.py
otxdet-0.3.2.dist-info/LICENSE
otxdet-0.3.2.dist-info/METADATA
otxdet-0.3.2.dist-info/WHEEL
otxdet-0.3.2.dist-info/top_level.txt
otxdet-0.3.2.dist-info/RECORD
