Metadata-Version: 2.1
Name: otxdet
Version: 0.3.2
Summary: Temporary OTX fork of MMDetection Object Detection toolbox
Home-page: https://github.com/openvinotoolkit/mmdetection
Author: OpenMMLab, Intel
Author-email: songki.choi@intel.com
License: Apache License 2.0
Keywords: computer vision,object detection,OpenVINO,OpenVINO training extensions,ONNX
Classifier: Development Status :: 5 - Production/Stable
Classifier: License :: OSI Approved :: Apache Software License
Classifier: Operating System :: OS Independent
Classifier: Programming Language :: Python :: 3
Classifier: Programming Language :: Python :: 3.6
Classifier: Programming Language :: Python :: 3.7
Classifier: Programming Language :: Python :: 3.8
License-File: LICENSE
Requires-Dist: matplotlib
Requires-Dist: mmcv-full (==1.3.14)
Requires-Dist: mmpycocotools
Requires-Dist: numpy
Requires-Dist: six
Requires-Dist: terminaltables
Requires-Dist: torch (<=1.9.0,>=1.7.1)
Requires-Dist: torchvision (<=0.10.0,>=0.8.1)
Requires-Dist: pytorchcv (==0.0.55)
Requires-Dist: tqdm
Requires-Dist: onnx (>=1.7.0)
Requires-Dist: onnxoptimizer
Requires-Dist: onnxruntime (>=1.1.2)
Requires-Dist: Shapely (==1.8.0)
Requires-Dist: editdistance
Provides-Extra: all
Requires-Dist: cython ; extra == 'all'
Requires-Dist: numpy ; extra == 'all'
Requires-Dist: torch (<=1.9.0,>=1.7.1) ; extra == 'all'
Requires-Dist: albumentations (==0.4.6) ; extra == 'all'
Requires-Dist: imagecorruptions ; extra == 'all'
Requires-Dist: ninja ; extra == 'all'
Requires-Dist: tensorboard ; extra == 'all'
Requires-Dist: imagesize (==1.2.0) ; extra == 'all'
Requires-Dist: PyYAML (>=5.4.1) ; extra == 'all'
Requires-Dist: sty (==1.0.0b12) ; extra == 'all'
Requires-Dist: scipy ; extra == 'all'
Requires-Dist: sklearn ; extra == 'all'
Requires-Dist: matplotlib ; extra == 'all'
Requires-Dist: mmcv-full (==1.3.14) ; extra == 'all'
Requires-Dist: mmpycocotools ; extra == 'all'
Requires-Dist: six ; extra == 'all'
Requires-Dist: terminaltables ; extra == 'all'
Requires-Dist: torchvision (<=0.10.0,>=0.8.1) ; extra == 'all'
Requires-Dist: pytorchcv (==0.0.55) ; extra == 'all'
Requires-Dist: tqdm ; extra == 'all'
Requires-Dist: onnx (>=1.7.0) ; extra == 'all'
Requires-Dist: onnxoptimizer ; extra == 'all'
Requires-Dist: onnxruntime (>=1.1.2) ; extra == 'all'
Requires-Dist: Shapely (==1.8.0) ; extra == 'all'
Requires-Dist: editdistance ; extra == 'all'
Requires-Dist: asynctest ; extra == 'all'
Requires-Dist: codecov ; extra == 'all'
Requires-Dist: flake8 ; extra == 'all'
Requires-Dist: interrogate ; extra == 'all'
Requires-Dist: isort (==4.3.21) ; extra == 'all'
Requires-Dist: kwarray ; extra == 'all'
Requires-Dist: pytest ; extra == 'all'
Requires-Dist: ubelt ; extra == 'all'
Requires-Dist: xdoctest (>=0.10.0) ; extra == 'all'
Requires-Dist: yapf ; extra == 'all'
Requires-Dist: testfixtures (>=6.14.2) ; extra == 'all'
Provides-Extra: build
Requires-Dist: cython ; extra == 'build'
Requires-Dist: numpy ; extra == 'build'
Requires-Dist: torch (<=1.9.0,>=1.7.1) ; extra == 'build'
Provides-Extra: optional
Requires-Dist: albumentations (==0.4.6) ; extra == 'optional'
Requires-Dist: imagecorruptions ; extra == 'optional'
Requires-Dist: ninja ; extra == 'optional'
Requires-Dist: tensorboard ; extra == 'optional'
Requires-Dist: imagesize (==1.2.0) ; extra == 'optional'
Requires-Dist: PyYAML (>=5.4.1) ; extra == 'optional'
Requires-Dist: sty (==1.0.0b12) ; extra == 'optional'
Requires-Dist: scipy ; extra == 'optional'
Requires-Dist: sklearn ; extra == 'optional'
Provides-Extra: tests
Requires-Dist: asynctest ; extra == 'tests'
Requires-Dist: codecov ; extra == 'tests'
Requires-Dist: flake8 ; extra == 'tests'
Requires-Dist: interrogate ; extra == 'tests'
Requires-Dist: isort (==4.3.21) ; extra == 'tests'
Requires-Dist: kwarray ; extra == 'tests'
Requires-Dist: pytest ; extra == 'tests'
Requires-Dist: ubelt ; extra == 'tests'
Requires-Dist: xdoctest (>=0.10.0) ; extra == 'tests'
Requires-Dist: yapf ; extra == 'tests'
Requires-Dist: testfixtures (>=6.14.2) ; extra == 'tests'
